pulumi_thalassa/__init__.py
pulumi_thalassa/_inputs.py
pulumi_thalassa/_utilities.py
pulumi_thalassa/block_volume.py
pulumi_thalassa/block_volume_attachment.py
pulumi_thalassa/cloud_init_template.py
pulumi_thalassa/dbaas_db_backupschedule.py
pulumi_thalassa/dbaas_db_cluster.py
pulumi_thalassa/dbaas_pg_database.py
pulumi_thalassa/dbaas_pg_roles.py
pulumi_thalassa/get_dbaas_db_backupschedule.py
pulumi_thalassa/get_dbaas_db_cluster.py
pulumi_thalassa/get_dbaas_pg_database.py
pulumi_thalassa/get_dbaas_pg_roles.py
pulumi_thalassa/get_iam_organisation_members.py
pulumi_thalassa/get_iam_role.py
pulumi_thalassa/get_iam_service_account.py
pulumi_thalassa/get_iam_team.py
pulumi_thalassa/get_kubernetes_cluster.py
pulumi_thalassa/get_kubernetes_version.py
pulumi_thalassa/get_machine_image.py
pulumi_thalassa/get_machine_type.py
pulumi_thalassa/get_objectstorage_bucket.py
pulumi_thalassa/get_organisation.py
pulumi_thalassa/get_region.py
pulumi_thalassa/get_regions.py
pulumi_thalassa/get_security_group.py
pulumi_thalassa/get_subnet.py
pulumi_thalassa/get_volume_type.py
pulumi_thalassa/get_vpc.py
pulumi_thalassa/iam_role.py
pulumi_thalassa/iam_role_binding.py
pulumi_thalassa/iam_service_account.py
pulumi_thalassa/iam_service_account_access_credential.py
pulumi_thalassa/iam_team.py
pulumi_thalassa/kubernetes_cluster.py
pulumi_thalassa/kubernetes_node_pool.py
pulumi_thalassa/loadbalancer.py
pulumi_thalassa/loadbalancer_listener.py
pulumi_thalassa/natgateway.py
pulumi_thalassa/objectstorage_bucket.py
pulumi_thalassa/outputs.py
pulumi_thalassa/provider.py
pulumi_thalassa/pulumi-plugin.json
pulumi_thalassa/py.typed
pulumi_thalassa/route_table.py
pulumi_thalassa/route_table_route.py
pulumi_thalassa/security_group.py
pulumi_thalassa/subnet.py
pulumi_thalassa/target_group.py
pulumi_thalassa/target_group_attachment.py
pulumi_thalassa/virtual_machine_instance.py
pulumi_thalassa/vpc.py
pulumi_thalassa/config/__init__.py
pulumi_thalassa/config/__init__.pyi
pulumi_thalassa/config/vars.py
pulumi_thalassa-0.3.0.dist-info/METADATA
pulumi_thalassa-0.3.0.dist-info/WHEEL
pulumi_thalassa-0.3.0.dist-info/top_level.txt
pulumi_thalassa-0.3.0.dist-info/RECORD
